mingzi/__init__.py
mingzi/_mingzi.py
mingzi/data.json
mingzi-1.2.3.dist-info/METADATA
mingzi-1.2.3.dist-info/WHEEL
mingzi-1.2.3.dist-info/licenses/LICENSE
mingzi-1.2.3.dist-info/RECORD
