Metadata-Version: 2.3
Name: mingzi
Version: 1.2.3
Summary: 这是一个用来生成随机中文姓名的包。This is a library for developers to use to generate random Chinese names.
Author-email: Aliyacs Souna <17818403529@139.com>
License-File: LICENSE
Classifier: License :: OSI Approved :: MIT License
Classifier: Operating System :: OS Independent
Classifier: Programming Language :: Python :: 3
Requires-Python: >=3.5
